gift_upload/__init__.py
gift_upload/upload.py
dedgeupload-0.0.1.dist-info/LICENSE
dedgeupload-0.0.1.dist-info/METADATA
dedgeupload-0.0.1.dist-info/WHEEL
dedgeupload-0.0.1.dist-info/top_level.txt
dedgeupload-0.0.1.dist-info/RECORD
