Metadata-Version: 2.1
Name: dedgeupload
Version: 0.0.1
Summary: A dedge upload package
Home-page: https://git.xiaojukeji.com/cf-terminal/v2x/upload.git
Author: liaoxinhui
Author-email: liaoxinhui@didiglobal.com
License: UNKNOWN
Project-URL: Bug Tracker, https://git.xiaojukeji.com/cf-terminal/v2x/upload/issues
Platform: UNKNOWN
Classifier: Programming Language :: Python :: 3
Classifier: License :: OSI Approved :: MIT License
Classifier: Operating System :: OS Independent
Requires-Python: >=3.6
License-File: LICENSE
